img2ascii/__init__.py
img2ascii/img2ascii.py
makeasciiart/__init__.py
makeasciiart-0.2.dist-info/LICENSE
makeasciiart-0.2.dist-info/METADATA
makeasciiart-0.2.dist-info/WHEEL
makeasciiart-0.2.dist-info/top_level.txt
makeasciiart-0.2.dist-info/RECORD
