Metadata-Version: 2.1
Name: makeasciiart
Version: 0.2
Summary: Convert image to ascii art
Home-page: https://github.com/sss1410002/makeasciiart
Author: SSS
Author-email: sss1410002@gmail.com
License: MIT
Keywords: opencv,ascii,ascii art
Platform: UNKNOWN
Classifier: Programming Language :: Python :: 3
Classifier: Programming Language :: Python :: 3.2
Classifier: Programming Language :: Python :: 3.3
Classifier: Programming Language :: Python :: 3.4
Classifier: Programming Language :: Python :: 3.5
Classifier: Programming Language :: Python :: 3.6
Classifier: Programming Language :: Python :: 3.7
Requires-Python: >=3
Requires-Dist: opencv-python
Requires-Dist: numpy
